cohere_aws/__init__.py
cohere_aws/chat.py
cohere_aws/classification.py
cohere_aws/client.py
cohere_aws/embeddings.py
cohere_aws/error.py
cohere_aws/generation.py
cohere_aws/mode.py
cohere_aws/rerank.py
cohere_aws/response.py
cohere_aws/summary.py
cohere_aws-0.8.16.dist-info/LICENSE
cohere_aws-0.8.16.dist-info/METADATA
cohere_aws-0.8.16.dist-info/WHEEL
cohere_aws-0.8.16.dist-info/top_level.txt
cohere_aws-0.8.16.dist-info/RECORD
