Metadata-Version: 2.1
Name: cohere-aws
Version: 0.8.16
Summary: A Python library for the Cohere endpoints in AWS Sagemaker & Bedrock
Home-page: https://github.com/cohere-ai/cohere-aws
Author: Cohere
Author-email: support@cohere.ai
Classifier: Programming Language :: Python :: 3
Classifier: License :: OSI Approved :: MIT License
Classifier: Operating System :: OS Independent
Requires-Python: >=3.9
License-File: LICENSE
Requires-Dist: boto3 >=1.28.57
Requires-Dist: sagemaker
